gr/cmd/__init__.py
gr/cmd/ch.py
gr/cmd/repo.py
gr/config.py
gr/main.py
gr/utils.py
gr_cli-0.4.0.dist-info/entry_points.txt
gr_cli-0.4.0.dist-info/WHEEL
gr_cli-0.4.0.dist-info/METADATA
gr_cli-0.4.0.dist-info/RECORD
