Metadata-Version: 2.1
Name: gr-cli
Version: 0.4.0
Summary: Gerrit's command line tool
Home-page: https://github.com/paul-nameless/gr
License: Unlicense
Author: Paul Nameless
Author-email: reacsdas@gmail.com
Requires-Python: >=3.9,<4.0
Classifier: License :: Other/Proprietary License
Classifier: Programming Language :: Python :: 3
Classifier: Programming Language :: Python :: 3.9
Requires-Dist: dateutils (>=0.6.12,<0.7.0)
Requires-Dist: humanize (>=3.4.1,<4.0.0)
Requires-Dist: requests (>=2.25.1,<3.0.0)
Requires-Dist: rich (>=10.1.0,<11.0.0)
Requires-Dist: typer (>=0.3.2,<0.4.0)
Project-URL: Repository, https://github.com/paul-nameless/gr
